<?xml version="1.0" encoding="UTF-8"?><record_update sys_domain="global" table="m2m_business_calendar_group_business_calendars">
    <m2m_business_calendar_group_business_calendars action="INSERT_OR_UPDATE">
        <business_calendar display_value="Fiscal Year">3f682e11d7222100738dc0da9e610353</business_calendar>
        <business_calendar_group display_value="Fiscal calendar">4704584d93718210868ab4de3bba10a0</business_calendar_group>
        <order>300</order>
        <sys_class_name>m2m_business_calendar_group_business_calendars</sys_class_name>
        <sys_created_by>admin</sys_created_by>
        <sys_created_on>2024-04-24 08:19:05</sys_created_on>
        <sys_domain>global</sys_domain>
        <sys_domain_path>/</sys_domain_path>
        <sys_id>1304584d93718210868ab4de3bba10aa</sys_id>
        <sys_mod_count>0</sys_mod_count>
        <sys_name>Fiscal Year.Fiscal calendar</sys_name>
        <sys_package display_value="NeedIt" source="x_58872_needit">6ead8e780f603200cd674f8ce1050ed1</sys_package>
        <sys_policy/>
        <sys_scope display_value="NeedIt">6ead8e780f603200cd674f8ce1050ed1</sys_scope>
        <sys_update_name>m2m_business_calendar_group_business_calendars_1304584d93718210868ab4de3bba10aa</sys_update_name>
        <sys_updated_by>admin</sys_updated_by>
        <sys_updated_on>2024-04-24 08:19:05</sys_updated_on>
    </m2m_business_calendar_group_business_calendars>
</record_update>
